setup.py
stdprojectexample/__init__.py
stdprojectexample.egg-info/PKG-INFO
stdprojectexample.egg-info/SOURCES.txt
stdprojectexample.egg-info/dependency_links.txt
stdprojectexample.egg-info/not-zip-safe
stdprojectexample.egg-info/requires.txt
stdprojectexample.egg-info/top_level.txt