Metadata-Version: 1.1
Name: stdprojectexample
Version: 0.0.0
Summary: Frib with Frobs with excellent Fermocity.
Home-page: https://github.com/openaps/stdprojectexample
Author: Maintainer McGroo
Author-email: work@maintain.er
License: UNKNOWN
Platform: UNKNOWN
Classifier: Development Status :: 3 - Alpha
Classifier: Intended Audience :: Developers
Classifier: Intended Audience :: Science/Research
Classifier: Programming Language :: Python
Classifier: Topic :: Scientific/Engineering
Classifier: Topic :: Software Development :: Libraries
